{
"code": 200,
"message": "홈 화면 데이터 조회에 성공했습니다",
"data": {
"webtoonsByCategory": {
    "IT": [
    {
        "id": 101,
        "title": "클라우드 비용 절감법",
        "image_url": "https://cdn.example.com/thumbnails/101.png"
    },
    {
        "id": 102,
        "title": "5G vs Wi‑Fi 6",
        "image_url": "https://cdn.example.com/thumbnails/102.png"
    },
    {
        "id": 103,
        "title": "빅데이터 분석 동향",
        "ai_author_id": "이작가",
        "image_url": "https://cdn.example.com/thumbnails/103.png"
    }
    ],
    "금융": [
    {
        "id": 201,
        "title": "디지털 자산 규제",
        "image_url": "https://cdn.example.com/thumbnails/201.png"
    },
    {
        "id": 202,
        "title": "핀테크 스타트업 현황",
        "image_url": "https://cdn.example.com/thumbnails/202.png"
    },
    {
        "id": 203,
        "title": "해외 송금 수수료 낮추기",
        "image_url": "https://cdn.example.com/thumbnails/203.png"
    }
    ]
}
}
}